artist_tracker/__init__.py
artist_tracker/cli.py
artist_tracker/config.py
artist_tracker/database.py
artist_tracker/exceptions.py
artist_tracker/profiler.py
artist_tracker/tracker.py
esh_tracker-0.1.0.dist-info/licenses/LICENSE
esh_tracker-0.1.0.dist-info/METADATA
esh_tracker-0.1.0.dist-info/WHEEL
esh_tracker-0.1.0.dist-info/entry_points.txt
esh_tracker-0.1.0.dist-info/top_level.txt
esh_tracker-0.1.0.dist-info/RECORD
