Metadata-Version: 2.4
Name: esh-tracker
Version: 0.1.0
Summary: Track new releases from your favorite Spotify artists
Author: opbenesh
License: MIT
Project-URL: Homepage, https://github.com/opbenesh/esh-tracker
Project-URL: Repository, https://github.com/opbenesh/esh-tracker
Project-URL: Issues, https://github.com/opbenesh/esh-tracker/issues
Keywords: spotify,music,releases,tracker,cli
Classifier: Development Status :: 4 - Beta
Classifier: Environment :: Console
Classifier: Intended Audience :: End Users/Desktop
Classifier: License :: OSI Approved :: MIT License
Classifier: Operating System :: OS Independent
Classifier: Programming Language :: Python :: 3
Classifier: Programming Language :: Python :: 3.7
Classifier: Programming Language :: Python :: 3.8
Classifier: Programming Language :: Python :: 3.9
Classifier: Programming Language :: Python :: 3.10
Classifier: Programming Language :: Python :: 3.11
Classifier: Programming Language :: Python :: 3.12
Classifier: Topic :: Multimedia :: Sound/Audio
Requires-Python: >=3.7
License-File: LICENSE
Requires-Dist: spotipy>=2.23.0
Requires-Dist: python-dotenv>=1.0.0
Requires-Dist: tqdm>=4.66.1
Provides-Extra: dev
Requires-Dist: mypy; extra == "dev"
Dynamic: license-file
